muffin_apiclient/__init__.py
muffin_apiclient/py.typed
muffin_apiclient-3.9.0.dist-info/LICENSE
muffin_apiclient-3.9.0.dist-info/METADATA
muffin_apiclient-3.9.0.dist-info/WHEEL
muffin_apiclient-3.9.0.dist-info/RECORD
