Metadata-Version: 2.3
Name: muffin-apiclient
Version: 3.9.0
Summary: It's a plugin for Muffin framework which provides support for external APIs
License: MIT
Keywords: apiclient,muffin,asyncio,trio,curio
Author: Kirill Klenov
Author-email: horneds@gmail.com
Requires-Python: >=3.9,<4.0
Classifier: Development Status :: 5 - Production/Stable
Classifier: Framework :: AsyncIO
Classifier: Framework :: Trio
Classifier: Intended Audience :: Developers
Classifier: License :: OSI Approved :: MIT License
Classifier: Programming Language :: Python
Classifier: Programming Language :: Python :: 3
Classifier: Programming Language :: Python :: 3.9
Classifier: Programming Language :: Python :: 3.10
Classifier: Programming Language :: Python :: 3.11
Classifier: Programming Language :: Python :: 3.12
Classifier: Programming Language :: Python :: 3.13
Classifier: Topic :: Internet :: WWW/HTTP
Provides-Extra: aiohttp
Provides-Extra: httpx
Requires-Dist: aio-apiclient
Requires-Dist: aiohttp ; extra == "aiohttp"
Requires-Dist: httpx ; extra == "httpx"
Requires-Dist: muffin
Project-URL: Homepage, https://github.com/klen/muffin-apiclient
Project-URL: Repository, https://github.com/klen/muffin-apiclient
